zsharp_pkg/ZSharp.py
zsharp_pkg/__init__.py
ZSharpPL-1.1.dist-info/LICENSE
ZSharpPL-1.1.dist-info/METADATA
ZSharpPL-1.1.dist-info/WHEEL
ZSharpPL-1.1.dist-info/top_level.txt
ZSharpPL-1.1.dist-info/RECORD
