Metadata-Version: 2.1
Name: ZSharpPL
Version: 1.1
Summary: Z-Sharp Language
Home-page: UNKNOWN
Author: Zanvok Corporation
License: UNKNOWN
Platform: UNKNOWN
Classifier: Programming Language :: Python :: 3
Classifier: License :: OSI Approved :: MIT License
Classifier: Operating System :: OS Independent
Requires-Python: >=3.7
License-File: LICENSE
